{"Seager": {"HRs": 16.0, "WAR": 0.9}, "Gonzales": {"ERA": 5.88, "WAR": -0.2}, "Paxton": {"Starts": 1.0, "WAR": 0.0}, "Moore": {"WAR": 0.7}, "France": {"WAR": 1.6}, "White": {"WAR": -0.7}, "Kelenic": {"OPS": 0.378, "WAR": -0.7}, "Gilbert": {"WAR": 0.8}, "Flexen": {"WAR": 1.4}, "Kikuchi": {"WAR": 2.1}, "Lewis": {"WAR": 0.5}, "Haniger": {"HRs": 20.0, "WAR": 1.5}, "Murphy": {"HRs": 7.0, "WAR": 0.5}, "Crawford": {"WAR": 2.9}, "Sheffield": {"WAR": -1.5}, "Trammel": {"WAR": -0.4}, "Dunn": {"WAR": 0.9}, "Fraley": {"WAR": 1.6}, "Middleton": {"WAR": 0.2}, "Haggerty": {"WAR": -0.3}, "Mariners": {"PitcherCount": 30.0, "NoHitCount": 2.0, "Wins": 48, "Losses": 43, "RunsScored": 371.0, "RunsAllowed": 421.0, "Hans": 5.9, "Gregory": 5.9, "ProjectedWins": 79.41143507483716}}